CohesionIntegration/__init__.py
CohesionIntegration/cohesion.py
CohesionIntegration-0.0.4.dist-info/METADATA
CohesionIntegration-0.0.4.dist-info/WHEEL
CohesionIntegration-0.0.4.dist-info/top_level.txt
CohesionIntegration-0.0.4.dist-info/RECORD
