Metadata-Version: 2.1
Name: CohesionIntegration
Version: 0.0.4
Summary: Cohesion integration package
Home-page: http://cohesion.regione.marche.it/cohesioninformativo
Author: Saverio Delpriori
Author-email: saveriodelpriori@gmail.com
License: MIT License
Platform: UNKNOWN
